{
  "name": "5GTANGO_CommPilot_NST",
  "description": "NST for the Communications Pilot WITHOUT SLA.",
  "vendor": "5gtango",
  "version": "2.0",
  "author": "5GTango",
  "usageState": "NOT_IN_USE",
  "SNSSAI_identifier": {
    "slice-service-type": "URLLC"
  },
  "slice_ns_subnets": [
    {
      "id": "comm-pilot-subnet",
      "nsd-name": "communication-pilot",
      "nsd-vendor": "quobis",
      "nsd-version": "0.5",
      "is-shared": false,
      "ingresses": [
        {
          "location": "9c21ec84-a834-404f-942e-43fa190a8734",
          "nap": "10.10.10.1/32"
        },
        {
          "location": "273c4fff-3c5f-406e-a1ee-450099d3a60c",
          "nap": "10.10.10.2/32"
        }
      ],
      "egresses": []
    }
  ],
  "slice_vld": [
  ]
}